BotHeads/__init__.py
BotHeads/botHeads.py
BotHeads-0.0.1.dist-info/METADATA
BotHeads-0.0.1.dist-info/WHEEL
BotHeads-0.0.1.dist-info/top_level.txt
BotHeads-0.0.1.dist-info/RECORD
