Metadata-Version: 2.1
Name: BotHeads
Version: 0.0.1
Summary: Chat Bots on the Go using openAI API with UI
Author: Abicii
Author-email: <abhijeettt.9876@gmail.com>
Keywords: python,chatbots,openai
Classifier: Development Status :: 1 - Planning
Classifier: Intended Audience :: Developers
Classifier: Programming Language :: Python :: 3
Classifier: Operating System :: Unix
Classifier: Operating System :: MacOS :: MacOS X
Classifier: Operating System :: Microsoft :: Windows
